{"type":"View","props":{"width":720,"top":0,"runtime":"script/ui/DefeatUI.js","right":0,"left":0,"height":1559,"bottom":0},"compId":2,"child":[{"type":"Image","props":{"y":0,"x":0,"top":0,"skin":"nine/img_block.png","sizeGrid":"3,3,3,3","right":0,"left":0,"bottom":0,"alpha":0.8},"compId":6},{"type":"Box","props":{"width":469,"top":300,"height":117,"centerX":-1},"compId":9,"child":[{"type":"Image","props":{"x":-0.5625,"skin":"common/img_fail.png"},"compId":7},{"type":"Image","props":{"y":0,"x":463.4375,"skin":"common/img_fail.png","scaleX":-1},"compId":8},{"type":"Label","props":{"text":"Fail","strokeColor":"#ffffff","stroke":5,"fontSize":120,"font":"SimHei","color":"#B8B1BE","centerY":-45,"centerX":3,"bold":true},"compId":3}]},{"type":"Label","props":{"y":0,"x":0,"var":"btn_rest","underlineColor":"#ffffff","underline":true,"text":"Again","fontSize":40,"font":"SimHei","color":"#ffffff","centerX":0,"bottom":300,"bold":true},"compId":5}],"loadList":["nine/img_block.png","common/img_fail.png"],"loadList3D":[]}